aiocertstream/__init__.py
aiocertstream/client.py
aiocertstream-0.1.6.dist-info/LICENSE
aiocertstream-0.1.6.dist-info/WHEEL
aiocertstream-0.1.6.dist-info/METADATA
aiocertstream-0.1.6.dist-info/RECORD
