Metadata-Version: 2.1
Name: aiocertstream
Version: 0.1.6
Summary: An async client for certstream.
Home-page: https://github.com/vcokltfre/aiocertstream
Keywords: certstream,asyncio
Author: vcokltfre
Author-email: vcokltfre@gmail.com
Requires-Python: >=3.8,<4.0
Classifier: Programming Language :: Python :: 3
Classifier: Programming Language :: Python :: 3.8
Classifier: Programming Language :: Python :: 3.9
Requires-Dist: aiohttp (>=3.7.4,<4.0.0)
Project-URL: Repository, https://github.com/vcokltfre/aiocertstream
